pdeprecator/__init__.py
pdeprecator/test_pdeprector.py
pdeprecator-0.0.1.dist-info/LICENSE
pdeprecator-0.0.1.dist-info/METADATA
pdeprecator-0.0.1.dist-info/WHEEL
pdeprecator-0.0.1.dist-info/top_level.txt
pdeprecator-0.0.1.dist-info/RECORD
