Metadata-Version: 2.1
Name: pdeprecator
Version: 0.0.1
Summary: A library provides a decorator deprecated_params that allows you to deprecate certain parameters in your class methods or function.
Home-page: https://github.com/Agent-Hellboy/pdeprecator
Author: Prince Roshan
Author-email: princekrroshan01@gmail.com
License: MIT
Keywords: deprecator,param-deprecator
Classifier: Programming Language :: Python :: 3.8
Classifier: Programming Language :: Python :: 3.9
Classifier: Programming Language :: Python :: 3.10
Classifier: Programming Language :: Python :: 3.11
Classifier: Programming Language :: Python :: 3.12
Classifier: Operating System :: OS Independent
Requires-Python: >=3.8
License-File: LICENSE
